{
  "entityType" : "ENTITY_GROUP",
  "entity" : {
    "additionalInfo" : {
      "description" : "Autogenerated Customer Users group with read-only permissions."
    },
    "configuration" : {
      "columns" : [ {
        "type" : "ENTITY_FIELD",
        "key" : "created_time",
        "sortOrder" : "DESC"
      }, {
        "type" : "ENTITY_FIELD",
        "key" : "first_name",
        "sortOrder" : "NONE"
      }, {
        "type" : "ENTITY_FIELD",
        "key" : "last_name",
        "sortOrder" : "NONE"
      }, {
        "type" : "ENTITY_FIELD",
        "key" : "email",
        "sortOrder" : "NONE"
      } ],
      "settings" : { },
      "actions" : { }
    },
    "edgeGroupAll" : false,
    "externalId" : null,
    "groupAll" : false,
    "id" : {
      "entityType" : "ENTITY_GROUP",
      "id" : "18710b60-8ada-11ef-9277-83a4a0978900"
    },
    "name" : "Customer Users",
    "ownerId" : {
      "entityType" : "CUSTOMER",
      "id" : "186c5070-8ada-11ef-9277-83a4a0978900"
    },
    "type" : "USER"
  },
  "relations" : [ ],
  "attributes" : {
    "SERVER_SCOPE" : [ ]
  },
  "groupEntities" : true,
  "permissions" : [ {
    "entityGroupId" : null,
    "entityGroupType" : null,
    "roleId" : {
      "entityType" : "ROLE",
      "id" : "cbc4fa10-e236-11ef-bee0-ed63ca0e6f37"
    },
    "tenantId" : {
      "entityType" : "TENANT",
      "id" : "79f36d30-0064-11ee-bc2f-7f25383766f4"
    },
    "userGroupId" : {
      "entityType" : "ENTITY_GROUP",
      "id" : "18710b60-8ada-11ef-9277-83a4a0978900"
    },
    "createdTime" : 1728985478941,
    "id" : {
      "entityType" : "GROUP_PERMISSION",
      "id" : "18721cd0-8ada-11ef-9277-83a4a0978900"
    },
    "name" : "GENERIC_[18710b60-8ada-11ef-9277-83a4a0978900]_[cbc4fa10-e236-11ef-bee0-ed63ca0e6f37]",
    "public" : false
  } ]
}