{
  "entityType" : "NOTIFICATION_RULE",
  "entity" : {
    "additionalConfig" : {
      "description" : "Send notification to tenant admins when device is created"
    },
    "enabled" : true,
    "externalId" : null,
    "id" : {
      "entityType" : "NOTIFICATION_RULE",
      "id" : "54c9e1a0-84ad-11ef-b1ec-fbb894068fb0"
    },
    "name" : "Device created",
    "recipientsConfig" : {
      "targets" : [ "54c6fb70-84ad-11ef-b1ec-fbb894068fb0" ],
      "triggerType" : "ENTITY_ACTION"
    },
    "templateId" : {
      "entityType" : "NOTIFICATION_TEMPLATE",
      "id" : "54c99380-84ad-11ef-b1ec-fbb894068fb0"
    },
    "triggerConfig" : {
      "triggerType" : "ENTITY_ACTION",
      "created" : true,
      "deleted" : false,
      "entityTypes" : [ "DEVICE" ],
      "updated" : false,
      "triggerType" : "ENTITY_ACTION"
    },
    "triggerType" : "ENTITY_ACTION"
  }
}