{
  "entityType" : "ASSET",
  "entity" : {
    "additionalInfo" : null,
    "assetProfileId" : {
      "entityType" : "ASSET_PROFILE",
      "id" : "81651140-3052-11ee-afc0-0770905e80c9"
    },
    "customerId" : {
      "entityType" : "CUSTOMER",
      "id" : "13814000-1dd2-11b2-8080-808080808080"
    },
    "externalId" : null,
    "id" : {
      "entityType" : "ASSET",
      "id" : "b3bf1670-a01b-11ee-8b8d-fd4f145a8f2f"
    },
    "label" : null,
    "name" : "Main_edeecd45f4e1",
    "ownerId" : null,
    "type" : "TbServiceQueue"
  },
  "relations" : [ ],
  "attributes" : {
    "SERVER_SCOPE" : [ ]
  }
}