{
  "entityType" : "ENTITY_GROUP",
  "entity" : {
    "additionalInfo" : null,
    "configuration" : {
      "columns" : [ {
        "type" : "ENTITY_FIELD",
        "key" : "created_time",
        "sortOrder" : "DESC"
      }, {
        "type" : "ENTITY_FIELD",
        "key" : "name",
        "sortOrder" : "NONE"
      }, {
        "type" : "ENTITY_FIELD",
        "key" : "device_profile",
        "sortOrder" : "NONE"
      }, {
        "type" : "ENTITY_FIELD",
        "key" : "label",
        "sortOrder" : "NONE"
      } ],
      "settings" : { },
      "actions" : { }
    },
    "edgeGroupAll" : false,
    "externalId" : {
      "entityType" : "ENTITY_GROUP",
      "id" : "186fabd0-8ada-11ef-9277-83a4a0978900"
    },
    "groupAll" : true,
    "id" : {
      "entityType" : "ENTITY_GROUP",
      "id" : "186fabd0-8ada-11ef-9277-83a4a0978900"
    },
    "name" : "All",
    "ownerId" : {
      "entityType" : "CUSTOMER",
      "id" : "186c5070-8ada-11ef-9277-83a4a0978900"
    },
    "type" : "DEVICE"
  },
  "relations" : [ ],
  "attributes" : {
    "SERVER_SCOPE" : [ ]
  },
  "groupEntities" : true
}