{
  "entityType" : "ROLE",
  "entity" : {
    "customerId" : {
      "entityType" : "CUSTOMER",
      "id" : "13814000-1dd2-11b2-8080-808080808080"
    },
    "externalId" : null,
    "name" : "Water Metering Read Only",
    "permissions" : [ "READ", "READ_ATTRIBUTES", "READ_CREDENTIALS", "READ_TELEMETRY" ],
    "type" : "GROUP",
    "additionalInfo" : null,
    "id" : {
      "entityType" : "ROLE",
      "id" : "df914a90-27f0-11ef-bfb3-cbf6848e1b4b"
    },
    "ownerId" : null
  },
  "relations" : [ ],
  "attributes" : {
    "SERVER_SCOPE" : [ ]
  }
}