{
  "entityType" : "DEVICE",
  "entity" : {
    "additionalInfo" : null,
    "customerId" : {
      "entityType" : "CUSTOMER",
      "id" : "f46af7e0-27f0-11ef-aa40-37783775a841"
    },
    "deviceData" : {
      "configuration" : {
        "type" : "DEFAULT"
      },
      "transportConfiguration" : {
        "type" : "DEFAULT"
      }
    },
    "deviceProfileId" : {
      "entityType" : "DEVICE_PROFILE",
      "id" : "f46615e0-27f0-11ef-aa40-37783775a841"
    },
    "externalId" : null,
    "firmwareId" : null,
    "id" : {
      "entityType" : "DEVICE",
      "id" : "f596f4c0-27f0-11ef-aa40-37783775a841"
    },
    "label" : "Smoke Sensor 4",
    "name" : "Smoke Sensor 4",
    "ownerId" : {
      "entityType" : "CUSTOMER",
      "id" : "f46af7e0-27f0-11ef-aa40-37783775a841"
    },
    "softwareId" : null,
    "type" : "Smoke Sensor"
  },
  "credentials" : {
    "credentialsId" : "zGMAJA6cpWmrBrtXaTde",
    "credentialsType" : "ACCESS_TOKEN",
    "credentialsValue" : null
  },
  "relations" : [ {
    "additionalInfo" : null,
    "from" : {
      "entityType" : "ASSET",
      "id" : "f4886af0-27f0-11ef-aa40-37783775a841"
    },
    "to" : {
      "entityType" : "DEVICE",
      "id" : "f596f4c0-27f0-11ef-aa40-37783775a841"
    },
    "type" : "Contains",
    "typeGroup" : "COMMON"
  } ],
  "attributes" : {
    "SERVER_SCOPE" : [ {
      "booleanValue" : true,
      "doubleValue" : null,
      "jsonValue" : null,
      "key" : "active",
      "lastUpdateTs" : 1718110136652,
      "longValue" : null,
      "strValue" : null
    }, {
      "booleanValue" : null,
      "doubleValue" : null,
      "jsonValue" : null,
      "key" : "inactivityTimeout",
      "lastUpdateTs" : 1718110136614,
      "longValue" : 15768000000,
      "strValue" : null
    }, {
      "booleanValue" : null,
      "doubleValue" : null,
      "jsonValue" : null,
      "key" : "lastActivityTime",
      "lastUpdateTs" : 1718110136652,
      "longValue" : 1718110136635,
      "strValue" : null
    }, {
      "booleanValue" : null,
      "doubleValue" : null,
      "jsonValue" : null,
      "key" : "lowBatteryCriticalThreshold",
      "lastUpdateTs" : 1718110133807,
      "longValue" : 10,
      "strValue" : null
    }, {
      "booleanValue" : null,
      "doubleValue" : null,
      "jsonValue" : null,
      "key" : "lowBatteryMajorThreshold",
      "lastUpdateTs" : 1718110133807,
      "longValue" : 30,
      "strValue" : null
    }, {
      "booleanValue" : null,
      "doubleValue" : null,
      "jsonValue" : null,
      "key" : "state",
      "lastUpdateTs" : 1718110133886,
      "longValue" : null,
      "strValue" : "normal"
    }, {
      "booleanValue" : null,
      "doubleValue" : 0.1345,
      "jsonValue" : null,
      "key" : "xPos",
      "lastUpdateTs" : 1718110133807,
      "longValue" : null,
      "strValue" : null
    }, {
      "booleanValue" : null,
      "doubleValue" : 0.259,
      "jsonValue" : null,
      "key" : "yPos",
      "lastUpdateTs" : 1718110133807,
      "longValue" : null,
      "strValue" : null
    } ],
    "SHARED_SCOPE" : [ ]
  }
}