{
  "entityType" : "ENTITY_GROUP",
  "entity" : {
    "additionalInfo" : {
      "description" : ""
    },
    "configuration" : {
      "columns" : [ {
        "type" : "ENTITY_FIELD",
        "key" : "created_time",
        "sortOrder" : "DESC"
      }, {
        "type" : "ENTITY_FIELD",
        "key" : "name",
        "sortOrder" : "NONE"
      }, {
        "type" : "ENTITY_FIELD",
        "key" : "device_profile",
        "sortOrder" : "NONE"
      }, {
        "type" : "ENTITY_FIELD",
        "key" : "label",
        "sortOrder" : "NONE"
      } ],
      "settings" : { },
      "actions" : { }
    },
    "edgeGroupAll" : false,
    "externalId" : {
      "entityType" : "ENTITY_GROUP",
      "id" : "4f30cc70-7c9a-11ee-8433-99f55ce61826"
    },
    "groupAll" : false,
    "id" : {
      "entityType" : "ENTITY_GROUP",
      "id" : "4f30cc70-7c9a-11ee-8433-99f55ce61826"
    },
    "name" : "device group",
    "ownerId" : {
      "entityType" : "CUSTOMER",
      "id" : "79de9830-7c90-11ee-a37c-7b76ea86735e"
    },
    "type" : "DEVICE"
  },
  "relations" : [ ],
  "attributes" : {
    "SERVER_SCOPE" : [ ]
  },
  "groupEntities" : true
}