{
  "entityType" : "NOTIFICATION_TARGET",
  "entity" : {
    "configuration" : {
      "type" : "PLATFORM_USERS",
      "description" : null,
      "usersFilter" : {
        "type" : "USER_LIST",
        "usersIds" : [ "7960dcd0-bf64-11ee-a512-a1fae3f17cfd" ]
      }
    },
    "externalId" : {
      "entityType" : "NOTIFICATION_TARGET",
      "id" : "559cf430-bf5c-11ee-a1a0-97590464718e"
    },
    "id" : {
      "entityType" : "NOTIFICATION_TARGET",
      "id" : "559cf430-bf5c-11ee-a1a0-97590464718e"
    },
    "name" : "test notification recipients group"
  },
  "relations" : [ ],
  "attributes" : {
    "SERVER_SCOPE" : [ ]
  }
}