{
  "entityType" : "DEVICE",
  "entity" : {
    "additionalInfo" : null,
    "customerId" : {
      "entityType" : "CUSTOMER",
      "id" : "e73911e0-1cda-11ef-bb2b-eb245d4ffb88"
    },
    "deviceData" : {
      "configuration" : {
        "type" : "DEFAULT"
      },
      "transportConfiguration" : {
        "type" : "DEFAULT"
      }
    },
    "deviceProfileId" : {
      "entityType" : "DEVICE_PROFILE",
      "id" : "e730fb90-1cda-11ef-bb2b-eb245d4ffb88"
    },
    "externalId" : null,
    "firmwareId" : null,
    "id" : {
      "entityType" : "DEVICE",
      "id" : "e7838860-1cda-11ef-bb2b-eb245d4ffb88"
    },
    "label" : "Fruits",
    "name" : "Smart Shelf 557322",
    "ownerId" : {
      "entityType" : "CUSTOMER",
      "id" : "e73911e0-1cda-11ef-bb2b-eb245d4ffb88"
    },
    "softwareId" : null,
    "type" : "Smart Shelf"
  },
  "credentials" : {
    "credentialsId" : "Wk3YVNSQGBxWkdaeSKvg",
    "credentialsType" : "ACCESS_TOKEN",
    "credentialsValue" : null
  },
  "relations" : [ {
    "additionalInfo" : null,
    "from" : {
      "entityType" : "ASSET",
      "id" : "e757bd70-1cda-11ef-bb2b-eb245d4ffb88"
    },
    "to" : {
      "entityType" : "DEVICE",
      "id" : "e7838860-1cda-11ef-bb2b-eb245d4ffb88"
    },
    "type" : "Contains",
    "typeGroup" : "COMMON"
  } ],
  "attributes" : {
    "SERVER_SCOPE" : [ {
      "booleanValue" : true,
      "doubleValue" : null,
      "jsonValue" : null,
      "key" : "active",
      "lastUpdateTs" : 1716891203259,
      "longValue" : null,
      "strValue" : null
    }, {
      "booleanValue" : null,
      "doubleValue" : null,
      "jsonValue" : null,
      "key" : "inactivityTimeout",
      "lastUpdateTs" : 1716891203240,
      "longValue" : 15768000000,
      "strValue" : null
    }, {
      "booleanValue" : null,
      "doubleValue" : null,
      "jsonValue" : null,
      "key" : "lastActivityTime",
      "lastUpdateTs" : 1716891203259,
      "longValue" : 1716891203247,
      "strValue" : null
    }, {
      "booleanValue" : null,
      "doubleValue" : null,
      "jsonValue" : null,
      "key" : "lowWeightCriticalThreshold",
      "lastUpdateTs" : 1716891198481,
      "longValue" : 5,
      "strValue" : null
    }, {
      "booleanValue" : null,
      "doubleValue" : null,
      "jsonValue" : null,
      "key" : "lowWeightMajorThreshold",
      "lastUpdateTs" : 1716891198481,
      "longValue" : 15,
      "strValue" : null
    }, {
      "booleanValue" : null,
      "doubleValue" : null,
      "jsonValue" : null,
      "key" : "state",
      "lastUpdateTs" : 1716891212841,
      "longValue" : null,
      "strValue" : "normal"
    }, {
      "booleanValue" : null,
      "doubleValue" : 0.6895846593918546,
      "jsonValue" : null,
      "key" : "xPos",
      "lastUpdateTs" : 1716891198481,
      "longValue" : null,
      "strValue" : null
    }, {
      "booleanValue" : null,
      "doubleValue" : 0.6990715532286214,
      "jsonValue" : null,
      "key" : "yPos",
      "lastUpdateTs" : 1716891198481,
      "longValue" : null,
      "strValue" : null
    } ],
    "SHARED_SCOPE" : [ ]
  }
}